resquare/__init__.py
resquare-0.0.2.dist-info/WHEEL
resquare-0.0.2.dist-info/METADATA
resquare-0.0.2.dist-info/RECORD
